qnmfits/__init__.py
qnmfits/cce.py
qnmfits/qnmfits.py
qnmfits/read_qnms.py
qnmfits/utils.py
qnmfits/data/cce-catalog.json
qnmfits-2025.3.1.dist-info/METADATA
qnmfits-2025.3.1.dist-info/WHEEL
qnmfits-2025.3.1.dist-info/licenses/LICENSE
qnmfits-2025.3.1.dist-info/RECORD
