Metadata-Version: 2.4
Name: qnmfits
Version: 2025.3.1
Summary: Fitting of quasinormal modes to ringdown waveforms.
Project-URL: Homepage, https://github.com/sxs-collaboration/qnmfits
Project-URL: Documentation, https://qnmfits.readthedocs.io/
Author-email: Lorena Magaña Zertuche <lmaganaz@go.olemiss.edu>, Eliot Finch <efinch@caltech.edu>
License: MIT License
License-File: LICENSE
Classifier: Intended Audience :: Science/Research
Classifier: License :: OSI Approved :: MIT License
Classifier: Operating System :: OS Independent
Classifier: Programming Language :: Python :: 3
Classifier: Topic :: Scientific/Engineering :: Astronomy
Classifier: Topic :: Scientific/Engineering :: Physics
Requires-Dist: qnm>=0.4.4
Requires-Dist: scri
Requires-Dist: tqdm
